{"code":0,"message":"OK","data":[{"goodsId":0,"spanSize":4,"banners":["https://img1.baidu.com/it/u=2047592740,3850805467&fm=253&fmt=auto&app=138&f=JPEG?w=500&h=313","https://img0.baidu.com/it/u=2770049884,2095836720&fm=26&fmt=auto","https://img1.baidu.com/it/u=1296138340,3465179656&fm=253&fmt=auto&app=120&f=JPEG?w=960&h=600"]},{"goodsId":1,"text":"明星产品","imageUrl":"https://img1.baidu.com/it/u=1296138340,3465179656&fm=253&fmt=auto&app=120&f=JPEG?w=960&h=600","spanSize":4},{"goodsId":2,"text":"小米5C 64GB 移动版","imageUrl":"https://img2.baidu.com/it/u=3961853789,2541078350&fm=253&fmt=auto&app=138&f=JPEG?w=800&h=500","spanSize":2},{"goodsId":3,"text":"米家智能摄像机","imageUrl":"https://img0.baidu.com/it/u=1564419729,1451192749&fm=26&fmt=auto","spanSize":2},{"goodsId":4,"imageUrl":"https://img1.baidu.com/it/u=591350809,1405920118&fm=253&fmt=auto&app=138&f=JPEG?w=333&h=499","spanSize":2},{"goodsId":5,"imageUrl":"https://img1.baidu.com/it/u=2528004002,100655352&fm=253&fmt=auto&app=120&f=JPEG?w=640&h=960","spanSize":2},{"goodsId":6,"imageUrl":"https://img2.baidu.com/it/u=3423020700,3072058830&fm=253&fmt=auto&app=138&f=JPEG?w=500&h=750","spanSize":2},{"goodsId":7,"imageUrl":"https://img2.baidu.com/it/u=3366899449,2761462014&fm=253&fmt=auto&app=138&f=JPG?w=500&h=750","spanSize":2},{"goodsId":8,"text":"智能生活，从这里开始","spanSize":4}]}